LICENSE
MANIFEST.in
README.md
VERSION
requirements.txt
setup.py
online_fbank/__init__.py
online_fbank/online_fbank.py
online_fbank.egg-info/PKG-INFO
online_fbank.egg-info/SOURCES.txt
online_fbank.egg-info/dependency_links.txt
online_fbank.egg-info/requires.txt
online_fbank.egg-info/top_level.txt