Metadata-Version: 2.1
Name: online-fbank
Version: 0.0.4
Summary: Online Fbank
Home-page: https://github.com/pengzhendong/online-fbank
Author: Zhendong Peng
Author-email: pzd17@tsinghua.org.cn
License: UNKNOWN
Platform: UNKNOWN
Classifier: Programming Language :: Python :: 3
Classifier: Operating System :: OS Independent
Classifier: Topic :: Scientific/Engineering
License-File: LICENSE
